procgen2-0.10.7.dist-info/LICENSE
procgen2-0.10.7.dist-info/METADATA
procgen2-0.10.7.dist-info/top_level.txt
procgen2-0.10.7.dist-info/RECORD
procgen2-0.10.7.dist-info/WHEEL
procgen2.libs/libQt5Gui-29f737a9.so.5.9.7
procgen2.libs/libicudata-cb3ba60c.so.50.2
procgen2.libs/liblzma-004595ca.so.5.2.2
procgen2.libs/libharfbuzz-77c15733.so.0.10705.0
procgen2.libs/libbz2-a273e504.so.1.0.6
procgen2.libs/libpng15-ce838cd1.so.15.13.0
procgen2.libs/libpcre2-16-206d15d9.so.0.5.0
procgen2.libs/libpcre-9513aab5.so.1.2.0
procgen2.libs/libgraphite2-3fca41c8.so.3.0.1
procgen2.libs/libQt5Core-99b605ee.so.5.9.7
procgen2.libs/libselinux-0922c95c.so.1
procgen2.libs/libsystemd-9be61d21.so.0.6.0
procgen2.libs/libgcrypt-18957bae.so.11.8.2
procgen2.libs/libicui18n-97d01360.so.50.2
procgen2.libs/libcap-79733b59.so.2.22
procgen2.libs/libfreetype-c0e61f0c.so.6.14.0
procgen2.libs/libattr-4f2a9577.so.1.1.0
procgen2.libs/liblz4-af1653fb.so.1.8.3
procgen2.libs/libgpg-error-3f09c3c7.so.0.10.0
procgen2.libs/libicuuc-1796a535.so.50.2
procgen2.libs/libdw-0-780627ce.176.so
procgen2.libs/libelf-0-3d9de92a.176.so
procgen/interactive.py
procgen/state_test.py
procgen/__init__.py
procgen/env_test.py
procgen/env.py
procgen/version.txt
procgen/builder.py
procgen/gym_registration.py
procgen/data/assets/kenney/Ground/Snow/snowCliffAlt_left.png
procgen/data/assets/kenney/Ground/Snow/snowCenter_rounded.png
procgen/data/assets/kenney/Ground/Snow/snowCorner_left.png
procgen/data/assets/kenney/Ground/Snow/snowHalf.png
procgen/data/assets/kenney/Ground/Snow/snowCenter.png
procgen/data/assets/kenney/Ground/Snow/snowRight.png
procgen/data/assets/kenney/Ground/Snow/snowHill_right.png
procgen/data/assets/kenney/Ground/Snow/snowLeft.png
procgen/data/assets/kenney/Ground/Snow/snowCliffAlt_right.png
procgen/data/assets/kenney/Ground/Snow/snowCliff_left.png
procgen/data/assets/kenney/Ground/Snow/snowHalf_right.png
procgen/data/assets/kenney/Ground/Snow/snowCorner_right.png
procgen/data/assets/kenney/Ground/Snow/snowHalf_mid.png
procgen/data/assets/kenney/Ground/Snow/snow.png
procgen/data/assets/kenney/Ground/Snow/snowHill_left.png
